ap2/common/__init__.py
ap2/common/a2a_extension_utils.py
ap2/common/a2a_message_builder.py
ap2/common/artifact_utils.py
ap2/common/base_server_executor.py
ap2/common/function_call_resolver.py
ap2/common/message_utils.py
ap2/common/payment_remote_a2a_client.py
ap2/common/retrying_llm_agent.py
ap2/common/server.py
ap2/common/system_utils.py
ap2/common/validation.py
ap2/common/watch_log.py
ap2/types/__init__.py
ap2/types/contact_picker.py
ap2/types/mandate.py
ap2/types/payment_request.py
ap2-0.1.1.dist-info/licenses/LICENSE
ap2-0.1.1.dist-info/METADATA
ap2-0.1.1.dist-info/WHEEL
ap2-0.1.1.dist-info/top_level.txt
ap2-0.1.1.dist-info/RECORD
