Metadata-Version: 2.4
Name: ap2
Version: 0.1.1
Summary: Agent Payments Protocol (Python)
Author: whill
License: MIT
Project-URL: Homepage, https://github.com/whillhill/ap2
Project-URL: Repository, https://github.com/whillhill/ap2
Project-URL: Issues, https://github.com/whillhill/ap2/issues
Project-URL: Documentation, https://github.com/whillhill/ap2#readme
Keywords: payments,a2a,ap2
Classifier: Development Status :: 3 - Alpha
Classifier: Intended Audience :: Developers
Classifier: License :: OSI Approved :: MIT License
Classifier: Programming Language :: Python :: 3
Classifier: Programming Language :: Python :: 3 :: Only
Classifier: Programming Language :: Python :: 3.10
Classifier: Programming Language :: Python :: 3.11
Classifier: Programming Language :: Python :: 3.12
Classifier: Topic :: Software Development :: Libraries
Classifier: Topic :: Internet
Requires-Python: >=3.10
License-File: LICENSE
Requires-Dist: pydantic>=2.6
Provides-Extra: samples
Requires-Dist: a2a-sdk; extra == "samples"
Requires-Dist: google-adk; extra == "samples"
Requires-Dist: google-genai; extra == "samples"
Requires-Dist: httpx; extra == "samples"
Requires-Dist: requests; extra == "samples"
Requires-Dist: starlette; extra == "samples"
Requires-Dist: uvicorn; extra == "samples"
Provides-Extra: examples
Requires-Dist: a2a-sdk; extra == "examples"
Requires-Dist: google-adk; extra == "examples"
Requires-Dist: google-genai; extra == "examples"
Requires-Dist: httpx; extra == "examples"
Requires-Dist: requests; extra == "examples"
Requires-Dist: starlette; extra == "examples"
Requires-Dist: uvicorn; extra == "examples"
Dynamic: license-file
